ALU.v
module Mul(x, y, o);
	input [31:0] x;
	input [31:0] y;
	output reg [31:0] o;
	
	reg [9:0]eo;	
	reg [48:0] mo;
	
	always @ (x, y) begin
		
		eo = x[30:23] + y[30:23];		//Exponant
		mo = {1'b1, x[22:0]}*{1'b1, y[22:0]};
		
		o[31] = x[31] ^ y[31];			//Sign Bit
		
		//$display("%b", mo);
		
		if(mo[47]) begin			//If : ans is (11.XX) => (1.1XX)
			o[22:0] = mo[46 -: 23];
			o[30:23] = eo - 9'd126;
		end else begin				//Else : ans is (01.XX)
			o[22:0] = mo[45 -: 23];
			o[30:23] = eo - 8'd127;
		end
		if(x==0 | y==0) o = 32'b0;
	end
endmodule


module Div(x, y, o);
	input [31:0] x;
	input [31:0] y;
	output reg [31:0] o;
	
	reg [7:0]eo;
	reg [47:0]mx;
	reg [23:0]my;
	reg [47:0]mo;
	
	reg [47:0]tmpM;
	integer i;
	
	always @(x, y) begin
		if(x == 32'b0) o = 32'b0;			//Checking for the x/y == 0
		
		else begin					//If not hen procced
			eo = x[30:23] - y[30:23] + 8'd127;	//Subtracting the exponants
			
			mx = {1'b1, x[22:0], 24'b0};		//Padding 0s at the end of X
			my = {1'b1, y[22:0]};		
					
			if (y[22:0] != 0) begin			//Checking for Y=1
				tmpM = 48'b0;
				for(i=47; i>=0; i=i-1) begin	//Division of Mantisa
					if(tmpM < my) begin
						mo[i] = 1'b0;
					end else begin
						mo[i] = 1'b1;
						tmpM = tmpM-my;
					end
					tmpM = {tmpM, mx[i]};
				end
			end else mo = mx;
			if(y == 32'b0) eo = 8'b11111111;	//Here the infinity = +/- 2^128
			if(~mo[23]) begin			//CHecking for the 0.1XXXXX ans
				mo = mo << 1'b1;
				eo = eo - 1'b1;
			end
			o = {x[31]^y[31], eo, mo[22:0]};	
		end
	end	
endmodule


module Add(x, y, o);
	input [31:0] x;
	input [31:0] y;
	output reg [31:0] o;
	
	reg [9:0]eo;	
	reg [25:0] mo;
	reg [24:0] mx;
	reg [24:0] my;
	
	integer df, i, j;
	
	function [59:0] setExponant;				//Fuction to set the mantisa to right place
		input [31:0] x;
		input [31:0] y;
		begin
			df = x[30:23] - y[30:23];
			//$display("%d", df);
			eo = x[30:23];
			mx = {2'b01, x[22:0]};
			my = {2'b01, y[22:0]};
			for(i=0; i<25; i = i + 1) begin		//Shift the lower exponant to higher
				if(i+df < 24)
					my[i] = my[i+df];
				else
					my[i] = 1'b0;
			end
			setExponant = {eo, mx, my};
		end
	endfunction
	
	always @(x, y) begin
		if(x[30:23] > y[30:23]) begin			//Which one has bigger exponant
			{eo, mx, my} = setExponant(x, y);
		end else begin
			{eo, my, mx} = setExponant(y, x);
		end
		
		if(~(x[31] ^ y[31])) begin			//If (+a, +b) or (-a, -b)
			mo = mx + my;
			o[31] = (x[31])?1'b1:1'b0;
			if (~mo[23] | mo[24]) begin		//for (11.XXX) => (1.1XX * 2)
				eo = eo + 1;
				mo = mo >> 1'b1;
			end
		end else begin					//If (+a, -b) or (-a, +b)
		if((mx != my) | (x[30:23] != y[30:23])) begin	//If : is |a| != |b|
			
			mo = x[31] ? (my - mx) : (mx - my);
			o[31] = mo[25];
			mo = mo[25]? (~mo + 1'b1) : mo;		//If ans is -ve
			
//			if (mo[25] & ~mo[23]) begin		//If : is (1X0.XXX) => (1X.0XX * 2)
//				eo = eo + 1;
//				mo = mo >> 1'b1;
//			end else begin				//Else : not 1X0.XXX
				for(i=0; i<23; i=i+1) begin
				if (~mo[23]) begin			//for (0.00..01XX) => (1.XXX)*2^n
					eo = eo - 1;
					mo = mo << 1'b1;
				end else mo = mo;
				end
				if (mo[24] & mo[23]) begin	//for (11.XX) => (1.1XX)
					eo = eo + 1;
					mo = mo >> 1'b1;
				end
//			end
		end else begin					//Else : not |a| != |b|
			eo = 0;
			mo = 0;
			o[31] = 0;
		end			
		end
		o = {o[31], eo[7:0], mo[22:0]};
				
	end
	
endmodule

ALUtb.v
`include "ALU.v"
module ALUtb;
	reg [31:0]a;			
	reg [31:0]b;
	
	wire [31:0]c1;			//Output of Add
	wire [31:0]c2;			//Output of Mul
	wire [31:0]c3;			//Output of Div
	
	integer fo, i;
	
	reg [63:0]fi [0:1000];
	
	Add add(a, b, c1);
	Mul mul(a, b, c2);
	Div div(a, b, c3);
	
	initial begin
		
		$dumpfile("ALUtb.vcd");
		$dumpvars;
		
		fo = $fopen("Output.txt", "w");
		$readmemb("Inputs.mem", fi);
		for(i=1; i<=fi[0][61:0]; i = i + 1) begin
			a = fi[i][63:32];
			b = fi[i][31:0];
			#1
			$fdisplay(fo,"%b%b%b", c1, c2, c3);	//Giving back to Python in cascaded formate
		end
		$fclose(fo);
		$finish;
	end	
endmodule

ALUtb.vcd
$date
	Tue Aug 22 20:56:07 2023
$end
$version
	Icarus Verilog
$end
$timescale
	1s
$end
$scope module ALUtb $end
$var wire 32 ! c3 [31:0] $end
$var wire 32 " c2 [31:0] $end
$var wire 32 # c1 [31:0] $end
$var reg 32 $ a [31:0] $end
$var reg 32 % b [31:0] $end
$var integer 32 & fo [31:0] $end
$var integer 32 ' i [31:0] $end
$scope module add $end
$var wire 32 ( x [31:0] $end
$var wire 32 ) y [31:0] $end
$var reg 10 * eo [9:0] $end
$var reg 26 + mo [25:0] $end
$var reg 25 , mx [24:0] $end
$var reg 25 - my [24:0] $end
$var reg 32 . o [31:0] $end
$var integer 32 / df [31:0] $end
$var integer 32 0 i [31:0] $end
$scope function setExponant $end
$var reg 32 1 x [31:0] $end
$var reg 32 2 y [31:0] $end
$upscope $end
$upscope $end
$scope module div $end
$var wire 32 3 x [31:0] $end
$var wire 32 4 y [31:0] $end
$var reg 8 5 eo [7:0] $end
$var reg 48 6 mo [47:0] $end
$var reg 48 7 mx [47:0] $end
$var reg 24 8 my [23:0] $end
$var reg 32 9 o [31:0] $end
$var reg 48 : tmpM [47:0] $end
$var integer 32 ; i [31:0] $end
$upscope $end
$scope module mul $end
$var wire 32 < x [31:0] $end
$var wire 32 = y [31:0] $end
$var reg 10 > eo [9:0] $end
$var reg 49 ? mo [48:0] $end
$var reg 32 @ o [31:0] $end
$upscope $end
$upscope $end
$enddefinitions $end
#0
$dumpvars
b0 @
b10000000000000000000000000000000000000000000000 ?
b10000000 >
b1000000000000000000000000000000 =
b0 <
bx ;
bx :
b0 9
bx 8
bx 7
bx 6
bx 5
b1000000000000000000000000000000 4
b0 3
b0 2
b1000000000000000000000000000000 1
b11001 0
b10000000 /
b1000000000000000000000000000000 .
b100000000000000000000000 -
b0 ,
b100000000000000000000000 +
b10000000 *
b1000000000000000000000000000000 )
b0 (
b1 '
b10000000000000000000000000000011 &
b1000000000000000000000000000000 %
b0 $
b1000000000000000000000000000000 #
b0 "
b0 !
$end
#1
b1000000000011110000100010001000 #
b1000000000011110000100010001000 .
b100011110000100010001000 +
b11001 0
b111111011111101100111010 -
b1000000001010111010110 ,
b10000000 *
b10 /
b111111111111011111101100111010 1
b111110100000000101011101011010 2
b111110111111101010100010001101 "
b111110111111101010100010001101 @
b11111110101010001000110101010110000100001100100 ?
b11111100 >
b111110000000010101110001111100 !
b111110000000010101110001111100 9
b100000010101110001111100 6
b11111111111111111111111111111111 ;
b11101110111011111101000 :
b111111011111101100111010 8
b100000000101011101011010000000000000000000000000 7
b1111100 5
b111111111111011111101100111010 %
b111111111111011111101100111010 )
b111111111111011111101100111010 4
b111111111111011111101100111010 =
b111110100000000101011101011010 $
b111110100000000101011101011010 (
b111110100000000101011101011010 3
b111110100000000101011101011010 <
b10 '
#2
b111110100000110111010110010001 !
b111110100000110111010110010001 9
b100000110111010110010001 6
b11111111111111111111111111111111 ;
b101110111100001111100000 :
b111101111111010100010000 8
b111111101010100010001110000000000000000000000000 7
b1111101 5
b111111011101101010100001101000 "
b111111011101101010100001101000 @
b111101101010100001101000001111000110111011100000 ?
b1000000000110111100111110011001 #
b1000000000110111100111110011001 .
b100110111100111110011001 +
b11001 0
b111101111111010100010000 -
b1111111010101000100011 ,
b10000000 *
b111111111101111111010100010000 1
b111110111111101010100010001110 2
b111111111101111111010100010000 %
b111111111101111111010100010000 )
b111111111101111111010100010000 4
b111111111101111111010100010000 =
b111110111111101010100010001110 $
b111110111111101010100010001110 (
b111110111111101010100010001110 3
b111110111111101010100010001110 <
b11 '
#3
b1000000001001100010000110011110 #
b1000000001001100010000110011110 .
b101001100010000110011110 +
b11001 0
b111011100000010111010100 -
b10111100011110101101001 ,
b10000000 *
b1 /
b111111111011100000010111010100 1
b111111001111000111101011010010 2
b111111101011110011111001111001 "
b111111101011110011111001111001 @
b101011110011111001111001101101111100111111101000 ?
b11111101 >
b111110110010101011011100010010 !
b111110110010101011011100010010 9
b110010101011011100010010 6
b11111111111111111111111111111111 ;
b1110100010000101100011000 :
b111011100000010111010100 8
b101111000111101011010010000000000000000000000000 7
b1111101 5
b111111111011100000010111010100 %
b111111111011100000010111010100 )
b111111111011100000010111010100 4
b111111111011100000010111010100 =
b111111001111000111101011010010 $
b111111001111000111101011010010 (
b111111001111000111101011010010 3
b111111001111000111101011010010 <
b100 '
#4
b111111000011001011110010111000 !
b111111000011001011110010111000 9
b100011001011110010111000 6
b11111111111111111111111111111111 ;
b100011101111011100100000 :
b111000000101010110100010 8
b111101101010100001101010000000000000000000000000 7
b1111110 5
b111111110110000010010111011110 "
b111111110110000010010111011110 @
b110110000010010111011110110000011100010100010100 ?
b1000000001011011101010011101011 #
b1000000001011011101010011101011 .
b101011011101010011101011 +
b11001 0
b111000000101010110100010 -
b11110110101010000110101 ,
b10000000 *
b111111111000000101010110100010 1
b111111011101101010100001101010 2
b111111111000000101010110100010 %
b111111111000000101010110100010 )
b111111111000000101010110100010 4
b111111111000000101010110100010 =
b111111011101101010100001101010 $
b111111011101101010100001101010 (
b111111011101101010100001101010 3
b111111011101101010100001101010 <
b101 '
#5
b1000000001100101100101001101010 #
b1000000001100101100101001101010 .
b101100101100101001101010 +
b11001 0
b110011110001101110111100 -
b100101100111100100011000 ,
b10000000 *
b0 /
b111111110011110001101110111100 1
b111111100101100111100100011000 2
b111111111100110111100001101111 "
b111111111100110111100001101111 @
b11110011011110000110111101011100111010110100000 ?
b11111110 >
b111111001110011111111010110000 !
b111111001110011111111010110000 9
b101110011111111010110000 6
b11111111111111111111111111111111 ;
b1001111000110011011000000 :
b110011110001101110111100 8
b100101100111100100011000000000000000000000000000 7
b1111110 5
b111111110011110001101110111100 %
b111111110011110001101110111100 )
b111111110011110001101110111100 4
b111111110011110001101110111100 =
b111111100101100111100100011000 $
b111111100101100111100100011000 (
b111111100101100111100100011000 3
b111111100101100111100100011000 <
b110 '
#6
b111111011100000110011001100100 !
b111111011100000110011001100100 9
b111100000110011001100100 6
b11111111111111111111111111111111 ;
b1010001100100011101000000 :
b101110101001110110110000 8
b101011110011111001111010000000000000000000000000 7
b1111110 5
b111111111111110111111010101100 "
b111111111111110111111010101100 @
b11111111011111101010110011011111100010111100000 ?
b1000000001101001110111000010101 #
b1000000001101001110111000010101 .
b101101001110111000010101 +
b11001 0
b101110101001110110110000 -
b101011110011111001111010 ,
b10000000 *
b111111101110101001110110110000 1
b111111101011110011111001111010 2
b111111101110101001110110110000 %
b111111101110101001110110110000 )
b111111101110101001110110110000 4
b111111101110101001110110110000 =
b111111101011110011111001111010 $
b111111101011110011111001111010 (
b111111101011110011111001111010 3
b111111101011110011111001111010 <
b111 '
#7
b1000000001101000011011101001000 #
b1000000001101000011011101001000 .
b101101000011011101001000 +
b11001 0
b101000110010111000110110 -
b110001010100000001011010 ,
b10000000 *
b111111101000110010111000110110 1
b111111110001010100000001011010 2
b111111111110110111011100101000 "
b111111111110110111011100101000 @
b11111011011101110010100011110011011111011111100 ?
b111111100110101011100110110110 !
b111111100110101011100110110110 9
b100110101011100110110110 6
b11111111111111111111111111111111 ;
b1110000011111100111000 :
b101000110010111000110110 8
b110001010100000001011010000000000000000000000000 7
b1111111 5
b111111101000110010111000110110 %
b111111101000110010111000110110 )
b111111101000110010111000110110 4
b111111101000110010111000110110 =
b111111110001010100000001011010 $
b111111110001010100000001011010 (
b111111110001010100000001011010 3
b111111110001010100000001011010 <
b1000 '
#8
b111111110010011011001000011100 !
b111111110010011011001000011100 9
b110010011011001000011100 6
b11111111111111111111111111111111 ;
b1001010001110000000 :
b100010010010101111110000 8
b110110000010010111011110000000000000000000000000 7
b111111111001111010001010111001 "
b111111111001111010001010111001 @
b11100111101000101011100110011011100101000100000 ?
b1000000001100001010100011100111 #
b1000000001100001010100011100111 .
b101100001010100011100111 +
b11001 0
b100010010010101111110000 -
b110110000010010111011110 ,
b10000000 *
b111111100010010010101111110000 1
b111111110110000010010111011110 2
b111111100010010010101111110000 %
b111111100010010010101111110000 )
b111111100010010010101111110000 4
b111111100010010010101111110000 =
b111111110110000010010111011110 $
b111111110110000010010111011110 (
b111111110110000010010111011110 3
b111111110110000010010111011110 <
b1001 '
#9
b1000000001010100101000101001110 #
b1000000001010100101000101001110 .
b101010100101000101001110 +
b11001 0
b11011001111111111011111 -
b111001111010001010111110 ,
b10000000 *
b1 /
b111111111001111010001010111110 1
b111111010110011111111110111110 2
b111111110001010100000001011010 "
b111111110001010100000001011010 @
b110001010100000001011010000101000000101100000100 ?
b11111101 >
b1000000000010000000000111000101 !
b1000000000010000000000111000101 9
b100010000000000111000101 6
b11111111111111111111111111111111 ;
b100111001110100110010100 :
b110110011111111110111110 8
b111001111010001010111110000000000000000000000000 7
b10000000 5
b111111010110011111111110111110 %
b111111010110011111111110111110 )
b111111010110011111111110111110 4
b111111010110011111111110111110 =
b111111111001111010001010111110 $
b111111111001111010001010111110 (
b111111111001111010001010111110 3
b111111111001111010001010111110 <
b1010 '
#10
b1000000010001001111100011000110 !
b1000000010001001111100011000110 9
b110001001111100011000110 6
b11111111111111111111111111111111 ;
b10011011001001100000 :
b100111100011011101111000 8
b111100110111100001110000000000000000000000000000 7
b111111100101100111100100010110 "
b111111100101100111100100010110 @
b100101100111100100010110001000001000010010000000 ?
b1000000001000010100101000010110 #
b1000000001000010100101000010110 .
b101000010100101000010110 +
b11001 0
b10011110001101110111100 -
b111100110111100001110000 ,
b10000000 *
b111111111100110111100001110000 1
b111111000111100011011101111000 2
b111111000111100011011101111000 %
b111111000111100011011101111000 )
b111111000111100011011101111000 4
b111111000111100011011101111000 =
b111111111100110111100001110000 $
b111111111100110111100001110000 (
b111111111100110111100001110000 3
b111111111100110111100001110000 <
b1011 '
#11
b1000000000101011011011110110010 #
b1000000000101011011011110110010 .
b100101011011011110110010 +
b11001 0
b1011111111100000111000 -
b111110110111011100101100 ,
b10000000 *
b10 /
b111111111110110111011100101100 1
b111110101111111110000011100010 2
b111111001111000111101011010000 "
b111111001111000111101011010000 @
b101111000111101011010000000110011011010011011000 ?
b11111100 >
b1000000101001111011111111110111 !
b1000000101001111011111111110111 9
b101001111011111111110111 6
b11111111111111111111111111111111 ;
b1010011101100111111100100 :
b101111111110000011100010 8
b111110110111011100101100000000000000000000000000 7
b10000001 5
b111110101111111110000011100010 %
b111110101111111110000011100010 )
b111110101111111110000011100010 4
b111110101111111110000011100010 =
b111111111110110111011100101100 $
b111111111110110111011100101100 (
b111111111110110111011100101100 3
b111111111110110111011100101100 <
b1100 '
#12
b1000001011111100101000000001101 !
b1000001011111100101000000001101 9
b111111100101000000001101 6
b11111111111111111111111111111111 ;
b111111101000011111100000 :
b100000001001100001010000 8
b111111110111111010101100000000000000000000000000 7
b10000010 5
b111110100000000101011101011001 "
b111110100000000101011101011001 @
b100000000101011101011001000011011011010111000000 ?
b11111011 >
b1000000000001111100100011011011 #
b1000000000001111100100011011011 .
b100001111100100011011011 +
b11001 0
b100000001001100001010 -
b111111110111111010101100 ,
b10000000 *
b11 /
b111111111111110111111010101100 1
b111110000000001001100001010000 2
b111110000000001001100001010000 %
b111110000000001001100001010000 )
b111110000000001001100001010000 4
b111110000000001001100001010000 =
b111111111111110111111010101100 $
b111111111111110111111010101100 (
b111111111111110111111010101100 3
b111111111111110111111010101100 <
b1101 '
#13
b111111111011110110101110100010 #
b111111111011110110101110100010 .
b111011110110101110100010 +
b10111 0
b100000001001100001010 -
b1111111 *
b10111110000000001001100001010000 2
b10111110100000000101011101011001 "
b10111110100000000101011101011001 @
b11000001011111100101000000001101 !
b11000001011111100101000000001101 9
b11111111111111111111111111111111 ;
b111111101000011111100000 :
b10111110000000001001100001010000 %
b10111110000000001001100001010000 )
b10111110000000001001100001010000 4
b10111110000000001001100001010000 =
b1110 '
#14
b11000000101001111011111111110111 !
b11000000101001111011111111110111 9
b101001111011111111110111 6
b11111111111111111111111111111111 ;
b1010011101100111111100100 :
b101111111110000011100010 8
b111110110111011100101100000000000000000000000000 7
b10000001 5
b10111111001111000111101011010000 "
b10111111001111000111101011010000 @
b101111000111101011010000000110011011010011011000 ?
b11111100 >
b111111110010110111111011110100 #
b111111110010110111111011110100 .
b110010110111111011110100 +
b10111 0
b1011111111100000111000 -
b111110110111011100101100 ,
b10 /
b111111111110110111011100101100 1
b10111110101111111110000011100010 2
b10111110101111111110000011100010 %
b10111110101111111110000011100010 )
b10111110101111111110000011100010 4
b10111110101111111110000011100010 =
b111111111110110111011100101100 $
b111111111110110111011100101100 (
b111111111110110111011100101100 3
b111111111110110111011100101100 <
b1111 '
#15
b111111101001000101110010110100 #
b111111101001000101110010110100 .
b101001000101110010110100 +
b10111 0
b10011110001101110111100 -
b111100110111100001110000 ,
b1 /
b111111111100110111100001110000 1
b10111111000111100011011101111000 2
b10111111100101100111100100010110 "
b10111111100101100111100100010110 @
b100101100111100100010110001000001000010010000000 ?
b11111101 >
b11000000010001001111100011000110 !
b11000000010001001111100011000110 9
b110001001111100011000110 6
b11111111111111111111111111111111 ;
b10011011001001100000 :
b100111100011011101111000 8
b111100110111100001110000000000000000000000000000 7
b10000000 5
b10111111000111100011011101111000 %
b10111111000111100011011101111000 )
b10111111000111100011011101111000 4
b10111111000111100011011101111000 =
b111111111100110111100001110000 $
b111111111100110111100001110000 (
b111111111100110111100001110000 3
b111111111100110111100001110000 <
b10000 '
#16
b11000000000010000000000111000101 !
b11000000000010000000000111000101 9
b100010000000000111000101 6
b11111111111111111111111111111111 ;
b100111001110100110010100 :
b110110011111111110111110 8
b111001111010001010111110000000000000000000000000 7
b10111111110001010100000001011010 "
b10111111110001010100000001011010 @
b110001010100000001011010000101000000101100000100 ?
b111111011101010100010110111110 #
b111111011101010100010110111110 .
b1111110 *
b111101010100010110111110 +
b10111 0
b11011001111111111011111 -
b111001111010001010111110 ,
b111111111001111010001010111110 1
b10111111010110011111111110111110 2
b10111111010110011111111110111110 %
b10111111010110011111111110111110 )
b10111111010110011111111110111110 4
b10111111010110011111111110111110 =
b111111111001111010001010111110 $
b111111111001111010001010111110 (
b111111111001111010001010111110 3
b111111111001111010001010111110 <
b10001 '
#17
b111111000111011111001111011100 #
b111111000111011111001111011100 .
b100111011111001111011100 +
b10111 0
b100010010010101111110000 -
b110110000010010111011110 ,
b1111110 *
b0 /
b10111111100010010010101111110000 1
b111111110110000010010111011110 2
b10111111111001111010001010111001 "
b10111111111001111010001010111001 @
b11100111101000101011100110011011100101000100000 ?
b11111110 >
b10111111110010011011001000011100 !
b10111111110010011011001000011100 9
b110010011011001000011100 6
b11111111111111111111111111111111 ;
b1001010001110000000 :
b100010010010101111110000 8
b110110000010010111011110000000000000000000000000 7
b1111111 5
b10111111100010010010101111110000 %
b10111111100010010010101111110000 )
b10111111100010010010101111110000 4
b10111111100010010010101111110000 =
b111111110110000010010111011110 $
b111111110110000010010111011110 (
b111111110110000010010111011110 3
b111111110110000010010111011110 <
b10010 '
#18
b10111111100110101011100110110110 !
b10111111100110101011100110110110 9
b100110101011100110110110 6
b11111111111111111111111111111111 ;
b1110000011111100111000 :
b101000110010111000110110 8
b110001010100000001011010000000000000000000000000 7
b10111111111110110111011100101000 "
b10111111111110110111011100101000 @
b11111011011101110010100011110011011111011111100 ?
b111110100010000100100010010000 #
b111110100010000100100010010000 .
b100010000100100010010000 +
b10111 0
b101000110010111000110110 -
b110001010100000001011010 ,
b1111101 *
b10111111101000110010111000110110 1
b111111110001010100000001011010 2
b10111111101000110010111000110110 %
b10111111101000110010111000110110 )
b10111111101000110010111000110110 4
b10111111101000110010111000110110 =
b111111110001010100000001011010 $
b111111110001010100000001011010 (
b111111110001010100000001011010 3
b111111110001010100000001011010 <
b10011 '
#19
b10111101101101011111001101100000 #
b10111101101101011111001101100000 .
b101101011111001101100000 +
b10111 0
b101110101001110110110000 -
b101011110011111001111010 ,
b1111011 *
b10111111101110101001110110110000 1
b111111101011110011111001111010 2
b10111111111111110111111010101100 "
b10111111111111110111111010101100 @
b11111111011111101010110011011111100010111100000 ?
b10111111011100000110011001100100 !
b10111111011100000110011001100100 9
b1111110 5
b111100000110011001100100 6
b11111111111111111111111111111111 ;
b1010001100100011101000000 :
b101110101001110110110000 8
b101011110011111001111010000000000000000000000000 7
b10111111101110101001110110110000 %
b10111111101110101001110110110000 )
b10111111101110101001110110110000 4
b10111111101110101001110110110000 =
b111111101011110011111001111010 $
b111111101011110011111001111010 (
b111111101011110011111001111010 3
b111111101011110011111001111010 <
b10100 '
#20
b10111111001110011111111010110000 !
b10111111001110011111111010110000 9
b101110011111111010110000 6
b11111111111111111111111111111111 ;
b1001111000110011011000000 :
b110011110001101110111100 8
b100101100111100100011000000000000000000000000000 7
b1111110 5
b10111111111100110111100001101111 "
b10111111111100110111100001101111 @
b11110011011110000110111101011100111010110100000 ?
b10111110111000101000101010010000 #
b10111110111000101000101010010000 .
b111000101000101010010000 +
b10111 0
b110011110001101110111100 -
b100101100111100100011000 ,
b1111101 *
b10111111110011110001101110111100 1
b111111100101100111100100011000 2
b10111111110011110001101110111100 %
b10111111110011110001101110111100 )
b10111111110011110001101110111100 4
b10111111110011110001101110111100 =
b111111100101100111100100011000 $
b111111100101100111100100011000 (
b111111100101100111100100011000 3
b111111100101100111100100011000 <
b10101 '
#21
b10111111010010100000001011011010 #
b10111111010010100000001011011010 .
b110010100000001011011010 +
b10111 0
b111000000101010110100010 -
b11110110101010000110101 ,
b1111110 *
b1 /
b10111111111000000101010110100010 1
b111111011101101010100001101010 2
b10111111110110000010010111011110 "
b10111111110110000010010111011110 @
b110110000010010111011110110000011100010100010100 ?
b11111101 >
b10111111000011001011110010111000 !
b10111111000011001011110010111000 9
b100011001011110010111000 6
b11111111111111111111111111111111 ;
b100011101111011100100000 :
b111000000101010110100010 8
b111101101010100001101010000000000000000000000000 7
b10111111111000000101010110100010 %
b10111111111000000101010110100010 )
b10111111111000000101010110100010 4
b10111111111000000101010110100010 =
b111111011101101010100001101010 $
b111111011101101010100001101010 (
b111111011101101010100001101010 3
b111111011101101010100001101010 <
b10110 '
#22
b10111110110010101011011100010010 !
b10111110110010101011011100010010 9
b1111101 5
b110010101011011100010010 6
b11111111111111111111111111111111 ;
b1110100010000101100011000 :
b111011100000010111010100 8
b101111000111101011010010000000000000000000000000 7
b10111111101011110011111001111001 "
b10111111101011110011111001111001 @
b101011110011111001111001101101111100111111101000 ?
b10111111100011111100100001101011 #
b10111111100011111100100001101011 .
b100011111100100001101011 +
b10111 0
b111011100000010111010100 -
b10111100011110101101001 ,
b1111111 *
b10111111111011100000010111010100 1
b111111001111000111101011010010 2
b10111111111011100000010111010100 %
b10111111111011100000010111010100 )
b10111111111011100000010111010100 4
b10111111111011100000010111010100 =
b111111001111000111101011010010 $
b111111001111000111101011010010 (
b111111001111000111101011010010 3
b111111001111000111101011010010 <
b10111 '
#23
b10111111101110000100101011101101 #
b10111111101110000100101011101101 .
b101110000100101011101101 +
b10111 0
b111101111111010100010000 -
b1111111010101000100011 ,
b10 /
b10111111111101111111010100010000 1
b111110111111101010100010001110 2
b10111111011101101010100001101000 "
b10111111011101101010100001101000 @
b111101101010100001101000001111000110111011100000 ?
b11111100 >
b10111110100000110111010110010001 !
b10111110100000110111010110010001 9
b100000110111010110010001 6
b11111111111111111111111111111111 ;
b101110111100001111100000 :
b111101111111010100010000 8
b111111101010100010001110000000000000000000000000 7
b10111111111101111111010100010000 %
b10111111111101111111010100010000 )
b10111111111101111111010100010000 4
b10111111111101111111010100010000 =
b111110111111101010100010001110 $
b111110111111101010100010001110 (
b111110111111101010100010001110 3
b111110111111101010100010001110 <
b11000 '
#24
b10111110000000010101110001111100 !
b10111110000000010101110001111100 9
b1111100 5
b100000010101110001111100 6
b11111111111111111111111111111111 ;
b11101110111011111101000 :
b111111011111101100111010 8
b100000000101011101011010000000000000000000000000 7
b10111110111111101010100010001101 "
b10111110111111101010100010001101 @
b11111110101010001000110101010110000100001100100 ?
b10111111110111011110010101100100 #
b10111111110111011110010101100100 .
b110111011110010101100100 +
b10111 0
b111111011111101100111010 -
b1000000001010111010110 ,
b10111111111111011111101100111010 1
b111110100000000101011101011010 2
b10111111111111011111101100111010 %
b10111111111111011111101100111010 )
b10111111111111011111101100111010 4
b10111111111111011111101100111010 =
b111110100000000101011101011010 $
b111110100000000101011101011010 (
b111110100000000101011101011010 3
b111110100000000101011101011010 <
b11001 '
#25
b11000000000000000000000000000000 #
b11000000000000000000000000000000 .
b100000000000000000000000 +
b10111 0
b100000000000000000000000 -
b0 ,
b10000000 *
b110101 /
b11000000000000000000000000000000 1
b100101100011010011000100110000 2
b10100110000011010011000100110000 "
b10100110000011010011000100110000 @
b10001101001100010011000000000000000000000000000 ?
b11001011 >
b10100100100000000000000000000000 !
b10100100100000000000000000000000 9
b110100110001001100000000000000000000000000000 6
b100000000000000000000000 8
b100011010011000100110000000000000000000000000000 7
b1001001 5
b11000000000000000000000000000000 %
b11000000000000000000000000000000 )
b11000000000000000000000000000000 4
b11000000000000000000000000000000 =
b100101100011010011000100110000 $
b100101100011010011000100110000 (
b100101100011010011000100110000 3
b100101100011010011000100110000 <
b11010 '
#26
b111110000000010101110001111100 !
b111110000000010101110001111100 9
b100000010101110001111100 6
b11111111111111111111111111111111 ;
b11101110111011111101000 :
b111111011111101100111010 8
b100000000101011101011010000000000000000000000000 7
b1111100 5
b111110111111101010100010001101 "
b111110111111101010100010001101 @
b11111110101010001000110101010110000100001100100 ?
b11111100 >
b11000000000011110000100010001000 #
b11000000000011110000100010001000 .
b100011110000100010001000 +
b11001 0
b111111011111101100111010 -
b1000000001010111010110 ,
b10000000 *
b10 /
b10111111111111011111101100111010 1
b10111110100000000101011101011010 2
b10111111111111011111101100111010 %
b10111111111111011111101100111010 )
b10111111111111011111101100111010 4
b10111111111111011111101100111010 =
b10111110100000000101011101011010 $
b10111110100000000101011101011010 (
b10111110100000000101011101011010 3
b10111110100000000101011101011010 <
b11011 '
#27
b11000000000110111100111110011001 #
b11000000000110111100111110011001 .
b100110111100111110011001 +
b11001 0
b111101111111010100010000 -
b1111111010101000100011 ,
b10000000 *
b10111111111101111111010100010000 1
b10111110111111101010100010001110 2
b111111011101101010100001101000 "
b111111011101101010100001101000 @
b111101101010100001101000001111000110111011100000 ?
b111110100000110111010110010001 !
b111110100000110111010110010001 9
b100000110111010110010001 6
b11111111111111111111111111111111 ;
b101110111100001111100000 :
b111101111111010100010000 8
b111111101010100010001110000000000000000000000000 7
b1111101 5
b10111111111101111111010100010000 %
b10111111111101111111010100010000 )
b10111111111101111111010100010000 4
b10111111111101111111010100010000 =
b10111110111111101010100010001110 $
b10111110111111101010100010001110 (
b10111110111111101010100010001110 3
b10111110111111101010100010001110 <
b11100 '
#28
b111110110010101011011100010010 !
b111110110010101011011100010010 9
b110010101011011100010010 6
b11111111111111111111111111111111 ;
b1110100010000101100011000 :
b111011100000010111010100 8
b101111000111101011010010000000000000000000000000 7
b1111101 5
b111111101011110011111001111001 "
b111111101011110011111001111001 @
b101011110011111001111001101101111100111111101000 ?
b11111101 >
b11000000001001100010000110011110 #
b11000000001001100010000110011110 .
b101001100010000110011110 +
b11001 0
b111011100000010111010100 -
b10111100011110101101001 ,
b10000000 *
b1 /
b10111111111011100000010111010100 1
b10111111001111000111101011010010 2
b10111111111011100000010111010100 %
b10111111111011100000010111010100 )
b10111111111011100000010111010100 4
b10111111111011100000010111010100 =
b10111111001111000111101011010010 $
b10111111001111000111101011010010 (
b10111111001111000111101011010010 3
b10111111001111000111101011010010 <
b11101 '
#29
b11000000001011011101010011101011 #
b11000000001011011101010011101011 .
b101011011101010011101011 +
b11001 0
b111000000101010110100010 -
b11110110101010000110101 ,
b10000000 *
b10111111111000000101010110100010 1
b10111111011101101010100001101010 2
b111111110110000010010111011110 "
b111111110110000010010111011110 @
b110110000010010111011110110000011100010100010100 ?
b111111000011001011110010111000 !
b111111000011001011110010111000 9
b100011001011110010111000 6
b11111111111111111111111111111111 ;
b100011101111011100100000 :
b111000000101010110100010 8
b111101101010100001101010000000000000000000000000 7
b1111110 5
b10111111111000000101010110100010 %
b10111111111000000101010110100010 )
b10111111111000000101010110100010 4
b10111111111000000101010110100010 =
b10111111011101101010100001101010 $
b10111111011101101010100001101010 (
b10111111011101101010100001101010 3
b10111111011101101010100001101010 <
b11110 '
